spacy_alpino/__init__.py
spacy_alpino/alpino.py
spacy_alpino/alpino2ud.sh
spacy_alpino/universal_dependencies.xq
spacy_alpino-0.7.7.dist-info/LICENSE.txt
spacy_alpino-0.7.7.dist-info/METADATA
spacy_alpino-0.7.7.dist-info/WHEEL
spacy_alpino-0.7.7.dist-info/top_level.txt
spacy_alpino-0.7.7.dist-info/RECORD
