Metadata-Version: 2.1
Name: spacy-alpino
Version: 0.7.7
Summary: Alpino wrapper for spaCy
Home-page: https://github.com/KoichiYasuoka/spaCy-Alpino
Author: Koichi Yasuoka
Author-email: yasuoka@kanji.zinbun.kyoto-u.ac.jp
License: LGPL
Project-URL: Alpino, http://www.let.rug.nl/vannoord/alp/Alpino/
Project-URL: lassy2ud, https://github.com/gossebouma/lassy2ud
Project-URL: Source, https://github.com/KoichiYasuoka/spaCy-Alpino
Project-URL: Tracker, https://github.com/KoichiYasuoka/spaCy-Alpino/issues
Keywords: spacy nlp
Classifier: License :: OSI Approved :: GNU Library or Lesser General Public License (LGPL)
Classifier: Programming Language :: Python :: 3
Classifier: Operating System :: OS Independent
Classifier: Topic :: Text Processing :: Linguistic
Classifier: Natural Language :: Dutch
Requires-Python: >=3.6
License-File: LICENSE.txt
Requires-Dist: deplacy (>=2.1.0)
Requires-Dist: spacy (>=2.2.2)
